aiolocust/__init__.py
aiolocust/__main__.py
aiolocust/datatypes.py
aiolocust/http.py
aiolocust/main.py
aiolocust/runner.py
aiolocust/stats.py
aiolocust-0.1.6.dist-info/WHEEL
aiolocust-0.1.6.dist-info/entry_points.txt
aiolocust-0.1.6.dist-info/METADATA
aiolocust-0.1.6.dist-info/RECORD
