Metadata-Version: 2.3
Name: aiolocust
Version: 0.1.6
Summary: Add your description here
Author: Lars Holmberg
Author-email: Lars Holmberg <lars.holmberg@redshirt.se>
Classifier: Development Status :: 2 - Pre-Alpha
Classifier: License :: OSI Approved :: MIT License
Classifier: Operating System :: OS Independent
Classifier: Programming Language :: Python
Classifier: Intended Audience :: Developers
Classifier: Intended Audience :: System Administrators
Classifier: Topic :: Software Development :: Testing
Classifier: Topic :: Software Development :: Testing :: Traffic Generation
Requires-Dist: aiohttp>=3.13.3
Requires-Dist: rich>=14.2.0
Requires-Dist: uvloop>=0.22.1 ; sys_platform == 'linux'
Requires-Dist: uvloop>=0.22.1 ; sys_platform == 'darwin'
Requires-Dist: typer>=0.21.1
Requires-Python: >=3.14
